onchainpay_api/__init__.py
onchainpay_api/error.py
onchainpay_api/domains/__init__.py
onchainpay_api/domains/address_book/__init__.py
onchainpay_api/domains/advanced_account/__init__.py
onchainpay_api/domains/auto_swaps/__init__.py
onchainpay_api/domains/basic_actions/__init__.py
onchainpay_api/domains/blockchain_addresses/__init__.py
onchainpay_api/domains/crosschain_bridge/__init__.py
onchainpay_api/domains/crosschain_swaps/__init__.py
onchainpay_api/domains/invoices/__init__.py
onchainpay_api/domains/kyt/__init__.py
onchainpay_api/domains/orders/__init__.py
onchainpay_api/domains/orphan_transactions/__init__.py
onchainpay_api/domains/partners_api/__init__.py
onchainpay_api/domains/personal_addresses/__init__.py
onchainpay_api/domains/recurring_payments/__init__.py
onchainpay_api/domains/webhooks/__init__.py
onchainpay_api/domains/withdraws/__init__.py
onchainpay_api/resources/__init__.py
onchainpay_api/resources/constants.py
onchainpay_api/resources/requester.py
onchainpay_api/resources/response.py
onchainpay_api/resources/utils.py
onchainpay_api-0.0.8.dist-info/LICENSE
onchainpay_api-0.0.8.dist-info/METADATA
onchainpay_api-0.0.8.dist-info/WHEEL
onchainpay_api-0.0.8.dist-info/top_level.txt
onchainpay_api-0.0.8.dist-info/RECORD
