Metadata-Version: 2.1
Name: onchainpay-api
Version: 0.0.8
Summary: SDK for Onchainpay API
Home-page: https://github.com/onchainpay/python_sdk
Author: Onchainpay Team
Author-email: support@onchainpay.io
License: UNKNOWN
Project-URL: Bug Tracker, https://github.com/onchainpay/python_sdk/issues
Platform: UNKNOWN
Classifier: Programming Language :: Python :: 3
Classifier: License :: OSI Approved :: BSD License
Classifier: Operating System :: OS Independent
Requires-Python: >=3.6
License-File: LICENSE
Requires-Dist: requests >=2.28.0
